{
  "project_info": {
    "project_number": "544332088376",
    "project_id": "sibo-a0f68",
    "storage_bucket": "sibo-a0f68.appspot.com"
  },
  "client": [
    {
      "client_info": {
        "mobilesdk_app_id": "1:544332088376:android:36907b0b02eaaf33f9d2cd",
        "android_client_info": {
          "package_name": "edu.ib.sibo"
        }
      },
      "oauth_client": [
        {
          "client_id": "544332088376-43jhk6gku4q1fnpsf2ln1crvrll6b6io.apps.googleusercontent.com",
          "client_type": 3
        }
      ],
      "api_key": [
        {
          "current_key": "AIzaSyAozlaWcoafRCu-1vNS7vZTyK8OcCpCkQU"
        }
      ],
      "services": {
        "appinvite_service": {
          "other_platform_oauth_client": [
            {
              "client_id": "544332088376-43jhk6gku4q1fnpsf2ln1crvrll6b6io.apps.googleusercontent.com",
              "client_type": 3
            }
          ]
        }
      }
    }
  ],
  "configuration_version": "1"
}